Metadata-Version: 1.1
Name: Jarve
Version: 0.0.3
Summary: A module for A.I
Home-page: UNKNOWN
Author: Kittex0/Mohammed Daniyal
Author-email: kittex0@protonmail.com
License: MIT
Keywords: A.I
Platform: UNKNOWN
Classifier: Development Status :: 5 - Production/Stable
Classifier: Intended Audience :: Education
Classifier: Operating System :: Microsoft :: Windows :: Windows 10
Classifier: License :: OSI Approved :: MIT License
Classifier: Programming Language :: Python :: 3
